ytdl/main.py
ytdl/utils/__init__.py
ytdl/utils/audio.py
ytdl/utils/config.py
ytdl/utils/helper.py
ytdl/utils/playlist.py
ytdl/utils/video.py
ytdl_entrypoint.py
ytdl-1.0.0rc4.dist-info/entry_points.txt
ytdl-1.0.0rc4.dist-info/WHEEL
ytdl-1.0.0rc4.dist-info/METADATA
ytdl-1.0.0rc4.dist-info/RECORD
