Metadata-Version: 2.1
Name: ytdl
Version: 1.0.0rc4
Summary: 
Home-page: https://pypi.org/project/ytdl
License: MIT
Keywords: YouTube,Downloader,Utility
Author: Dong Nguyen
Author-email: ndaidong@gmail.com
Maintainer: Dong Nguyen
Maintainer-email: ndaidong@gmail.com
Requires-Python: >=3.8,<4.0
Classifier: License :: OSI Approved :: MIT License
Classifier: Programming Language :: Python :: 3
Classifier: Programming Language :: Python :: 3.8
Requires-Dist: bella (>=2.1.3,<3.0.0)
Requires-Dist: fire (>=0.3.1,<0.4.0)
Requires-Dist: python-youtube (>=0.6.0,<0.7.0)
Requires-Dist: pytube3 (>=9.6.4,<10.0.0)
Project-URL: Repository, https://github.com/ndaidong/ytdl
